LICENSE
MANIFEST.in
README.rst
ablk.py
setup.py
ablk.egg-info/PKG-INFO
ablk.egg-info/SOURCES.txt
ablk.egg-info/dependency_links.txt
ablk.egg-info/entry_points.txt
ablk.egg-info/requires.txt
ablk.egg-info/top_level.txt
ablk.egg-info/zip-safe