Metadata-Version: 1.1
Name: ablk
Version: 0.3
Summary: Terminal image viewer
Home-page: https://github.com/moertle/ablk
Author: Matthew Oertle
Author-email: moertle@gmail.com
License: MIT
Platform: UNKNOWN
Classifier: Development Status :: 4 - Beta
Classifier: Environment :: Console
Classifier: License :: OSI Approved :: MIT License
Classifier: Programming Language :: Python :: 3
Classifier: Topic :: Multimedia :: Graphics :: Viewers
